thredds_crawler/__init__.py
thredds_crawler/crawl.py
thredds_crawler/utils.py
thredds_crawler/tests/__init__.py
thredds_crawler/tests/test_crawler.py
thredds_crawler-1.5.4.dist-info/METADATA
thredds_crawler-1.5.4.dist-info/RECORD
thredds_crawler-1.5.4.dist-info/WHEEL
thredds_crawler-1.5.4.dist-info/top_level.txt
