Metadata-Version: 1.1
Name: thredds-crawler
Version: 1.5.4
Summary: A Python library for crawling THREDDS servers
Home-page: https://github.com/ioos/thredds_crawler
Author: Kyle Wilcox
Author-email: kyle@axiomdatascience.com
License: MIT
Platform: UNKNOWN
Classifier: Development Status :: 5 - Production/Stable
Classifier: Intended Audience :: Developers
Classifier: Intended Audience :: Science/Research
Classifier: License :: OSI Approved :: GNU General Public License v3 (GPLv3)
Classifier: Operating System :: OS Independent
Classifier: Programming Language :: Python
Classifier: Topic :: Scientific/Engineering
